cameralyze/__init__.py
cameralyze/statics.py
cameralyze/helpers/__init__.py
cameralyze/helpers/database/__init__.py
cameralyze/helpers/database/postgre.py
cameralyze/helpers/slack/__init__.py
cameralyze/helpers/slack/message.py
cameralyze_toolkit-0.0.2.dist-info/LICENSE
cameralyze_toolkit-0.0.2.dist-info/METADATA
cameralyze_toolkit-0.0.2.dist-info/WHEEL
cameralyze_toolkit-0.0.2.dist-info/top_level.txt
cameralyze_toolkit-0.0.2.dist-info/RECORD
