Metadata-Version: 2.1
Name: cameralyze-toolkit
Version: 0.0.2
Summary: Cameralyze - Python Toolkit
Home-page: https://github.com/abdullahkulcu/Camper-Logger-Exception
Author: Cameralyze
Author-email: info@cameralyze.com
License: UNKNOWN
Platform: UNKNOWN
Classifier: Programming Language :: Python :: 3.7
Classifier: License :: OSI Approved :: MIT License
Classifier: Operating System :: OS Independent
Requires-Dist: psycopg2-binary (==2.8.6)
Requires-Dist: requests
